deltafi/__init__.py
deltafi/action.py
deltafi/actioneventqueue.py
deltafi/actiontype.py
deltafi/domain.py
deltafi/exception.py
deltafi/genericmodel.py
deltafi/graphql.py
deltafi/input.py
deltafi/logger.py
deltafi/lookuptable.py
deltafi/metric.py
deltafi/plugin.py
deltafi/result.py
deltafi/resultmessage.py
deltafi/storage.py
deltafi/types.py
deltafi/test_kit/__init__.py
deltafi/test_kit/assertions.py
deltafi/test_kit/compare_helpers.py
deltafi/test_kit/constants.py
deltafi/test_kit/egress.py
deltafi/test_kit/framework.py
deltafi/test_kit/timed_ingress.py
deltafi/test_kit/transform.py
deltafi-2.49.0.dist-info/METADATA
deltafi-2.49.0.dist-info/WHEEL
deltafi-2.49.0.dist-info/RECORD
